oauthlogin/__init__.py
oauthlogin/admin.py
oauthlogin/apps.py
oauthlogin/exceptions.py
oauthlogin/migrations/0001_initial.py
oauthlogin/migrations/0002_alter_oauthconnection_options_and_more.py
oauthlogin/migrations/0003_alter_oauthconnection_access_token_and_more.py
oauthlogin/migrations/__init__.py
oauthlogin/models.py
oauthlogin/providers.py
oauthlogin/templates/oauthlogin/error.html
oauthlogin/urls.py
oauthlogin/views.py
django_oauth_login-0.2.4.dist-info/LICENSE
django_oauth_login-0.2.4.dist-info/METADATA
django_oauth_login-0.2.4.dist-info/WHEEL
django_oauth_login-0.2.4.dist-info/RECORD
