Metadata-Version: 2.1
Name: django-oauth-login
Version: 0.2.4
Summary: 
Home-page: https://github.com/dropseed/django-oauth-login
License: MIT
Author: Dave Gaeddert
Author-email: dave.gaeddert@dropseed.dev
Requires-Python: >=3.8,<4.0
Classifier: Environment :: Web Environment
Classifier: Framework :: Django
Classifier: Framework :: Django :: 3
Classifier: Framework :: Django :: 4
Classifier: Intended Audience :: Developers
Classifier: License :: OSI Approved :: MIT License
Classifier: Operating System :: OS Independent
Classifier: Programming Language :: Python
Classifier: Programming Language :: Python :: 3
Classifier: Programming Language :: Python :: 3.8
Classifier: Programming Language :: Python :: 3.9
Classifier: Programming Language :: Python :: 3.10
Classifier: Programming Language :: Python :: 3.11
Classifier: Programming Language :: Python :: 3 :: Only
Project-URL: Documentation, https://github.com/dropseed/django-oauth-login
Project-URL: Repository, https://github.com/dropseed/django-oauth-login
